LICENSE
MANIFEST.in
README.md
setup.py
django_any_backend/__init__.py
django_any_backend/admin.py
django_any_backend/client.py
django_any_backend/distinct.py
django_any_backend/filters.py
django_any_backend/paginators.py
django_any_backend/routers.py
django_any_backend/sorting.py
django_any_backend/testcases.py
django_any_backend/update.py
django_any_backend/utils.py
django_any_backend.egg-info/PKG-INFO
django_any_backend.egg-info/SOURCES.txt
django_any_backend.egg-info/dependency_links.txt
django_any_backend.egg-info/top_level.txt
django_any_backend/backends/__init__.py
django_any_backend/backends/base.py
django_any_backend/backends/compiler.py
django_any_backend/backends/creation.py
django_any_backend/backends/cursor.py
django_any_backend/backends/database.py
django_any_backend/backends/features.py
django_any_backend/backends/introspection.py
django_any_backend/backends/operations.py
django_any_backend/backends/schema.py
django_any_backend/management/__init__.py
django_any_backend/management/commands/__init__.py
django_any_backend/management/commands/loaddatabulk.py
pickle_db/__init__.py
pickle_db/client.py
pickle_db/introspection.py
pickle_db/schema.py
sql_testapp/__init__.py
sql_testapp/admin.py
sql_testapp/apps.py
sql_testapp/models.py
sql_testapp/urls.py
sql_testapp/views.py
sql_testapp/migrations/0001_initial.py
sql_testapp/migrations/0002_auto_20160313_2322.py
sql_testapp/migrations/__init__.py
testapp/__init__.py
testapp/admin.py
testapp/apps.py
testapp/models.py
testapp/urls.py
testapp/views.py
testapp/migrations/0001_initial.py
testapp/migrations/__init__.py
tests/__init__.py
tests/base.py
tests/admin_change_list/__init__.py
tests/admin_change_list/bak.py
tests/model/__init__.py
tests/model/tests.py
tests/queryset/__init__.py
tests/queryset/tests.py
testsite/__init__.py
testsite/settings.py
testsite/urls.py
testsite/wsgi.py