Metadata-Version: 1.1
Name: django-any-backend
Version: 0.1
Summary: Enable custom backends in Django
Home-page: https://github.com/primal100/django_any_backend
Author: Paul Martin
Author-email: greatestloginnameever@gmail.com
License: UNKNOWN
Platform: UNKNOWN
Classifier: Development Status :: 4 - Beta
Classifier: Environment :: Web Environment
Classifier: Framework :: Django
Classifier: Intended Audience :: Developers
Classifier: License :: OSI Approved :: BSD License
Classifier: Operating System :: OS Independent
Classifier: Programming Language :: Python
Classifier: Programming Language :: Python :: 2
Classifier: Programming Language :: Python :: 3
Classifier: Topic :: Database
Classifier: Topic :: Software Development :: Libraries :: Python Modules
